{"status":"ok","alive":true,"strategy":"tsmom_multi/4H/SMA200/band0.35/tv0.6/equal-weight","universe":["BTC/USD","ETH/USD","SOL/USD","XRP/USD","DOT/USD","AVAX/USD"],"ticks":76,"run_hours":329.2,"run_days":13.72,"last_tick":"2026-07-13T11:24:24+00:00","last_tick_age_hours":0.0,"start_equity":999.84,"equity":969.32,"cash":969.23,"total_return_pct":-3.052,"peak_equity":1005.88,"current_drawdown_pct":-3.63,"max_drawdown_pct":-3.63,"live_sharpe_annualized":-7.45,"rebalance_ticks":28,"total_fills":49,"open_positions":4,"positions":[{"symbol":"BTC/USD","direction":"flat","qty":0.0,"target_lev":0.0,"entry":0.0,"last_action":"hold"},{"symbol":"ETH/USD","direction":"LONG","qty":0.027168,"target_lev":0.302,"entry":1786.03,"last_action":"hold"},{"symbol":"SOL/USD","direction":"flat","qty":0.0,"target_lev":0.0,"entry":0.0,"last_action":"hold"},{"symbol":"XRP/USD","direction":"SHORT","qty":-71.156668,"target_lev":-0.602,"entry":1.08,"last_action":"hold"},{"symbol":"DOT/USD","direction":"SHORT","qty":-80.915165,"target_lev":-0.356,"entry":0.83,"last_action":"hold"},{"symbol":"AVAX/USD","direction":"SHORT","qty":-11.795605,"target_lev":-0.368,"entry":6.54,"last_action":"hold"}],"recent_fills":[{"ts":"2026-07-13T07:31:31+00:00","symbol":"BTC/USD","filled_btc":-0.001708,"price":62756.18},{"ts":"2026-07-13T07:31:31+00:00","symbol":"ETH/USD","filled_btc":-0.049947,"price":1779.68},{"ts":"2026-07-13T07:31:31+00:00","symbol":"DOT/USD","filled_btc":-73.532912,"price":0.83},{"ts":"2026-07-13T03:48:17+00:00","symbol":"XRP/USD","filled_btc":-53.212007,"price":1.09},{"ts":"2026-07-12T03:45:40+00:00","symbol":"BTC/USD","filled_btc":-0.001151,"price":63769.19},{"ts":"2026-07-12T03:45:40+00:00","symbol":"AVAX/USD","filled_btc":-11.795605,"price":6.55},{"ts":"2026-07-10T14:47:09+00:00","symbol":"BTC/USD","filled_btc":0.00112,"price":64381.9},{"ts":"2026-07-10T14:47:09+00:00","symbol":"ETH/USD","filled_btc":0.038788,"price":1799.56}],"equity_curve":[999.84,997.75,999.4,999.37,1000.42,1002.7,999.32,997.13,998.12,998.81,995.52,995.38,995.65,996.05,998.13,996.52,996.81,996.51,996.5,996.61,998.5,996.46,998.98,999.6,999.57,999.28,998.51,1005.4,1005.88,995.55,996.39,995.02,997.51,997.24,999.36,993.5,997.13,998.9,992.75,992.61,993.33,995.67,993.86,989.58,982.3,981.64,980.7,982.19,979.13,979.31,979.33,973.96,974.43,975.06,974.68,972.3,972.3,972.09,973.42,971.78,971.5,972.57,972.41,972.66,972.7,973.68,974.69,970.96,973.7,974.08,974.02,975.46,975.22,974.23,970.5,969.32],"generated_at":"2026-07-13T11:24:39+00:00"}
